captum/__init__.py
captum/_utils/__init__.py
captum/_utils/av.py
captum/_utils/common.py
captum/_utils/gradient.py
captum/_utils/progress.py
captum/_utils/sample_gradient.py
captum/_utils/typing.py
captum/_utils/models/__init__.py
captum/_utils/models/model.py
captum/_utils/models/linear_model/__init__.py
captum/_utils/models/linear_model/model.py
captum/_utils/models/linear_model/train.py
captum/attr/__init__.py
captum/attr/_core/__init__.py
captum/attr/_core/deep_lift.py
captum/attr/_core/feature_ablation.py
captum/attr/_core/feature_permutation.py
captum/attr/_core/gradient_shap.py
captum/attr/_core/guided_backprop_deconvnet.py
captum/attr/_core/guided_grad_cam.py
captum/attr/_core/input_x_gradient.py
captum/attr/_core/integrated_gradients.py
captum/attr/_core/kernel_shap.py
captum/attr/_core/lime.py
captum/attr/_core/lrp.py
captum/attr/_core/noise_tunnel.py
captum/attr/_core/occlusion.py
captum/attr/_core/saliency.py
captum/attr/_core/shapley_value.py
captum/attr/_core/layer/__init__.py
captum/attr/_core/layer/grad_cam.py
captum/attr/_core/layer/internal_influence.py
captum/attr/_core/layer/layer_activation.py
captum/attr/_core/layer/layer_conductance.py
captum/attr/_core/layer/layer_deep_lift.py
captum/attr/_core/layer/layer_feature_ablation.py
captum/attr/_core/layer/layer_gradient_shap.py
captum/attr/_core/layer/layer_gradient_x_activation.py
captum/attr/_core/layer/layer_integrated_gradients.py
captum/attr/_core/layer/layer_lrp.py
captum/attr/_core/neuron/__init__.py
captum/attr/_core/neuron/neuron_conductance.py
captum/attr/_core/neuron/neuron_deep_lift.py
captum/attr/_core/neuron/neuron_feature_ablation.py
captum/attr/_core/neuron/neuron_gradient.py
captum/attr/_core/neuron/neuron_gradient_shap.py
captum/attr/_core/neuron/neuron_guided_backprop_deconvnet.py
captum/attr/_core/neuron/neuron_integrated_gradients.py
captum/attr/_models/__init__.py
captum/attr/_models/base.py
captum/attr/_models/pytext.py
captum/attr/_utils/__init__.py
pear_xai-0.0.10.dist-info/LICENSE
pear_xai-0.0.10.dist-info/METADATA
pear_xai-0.0.10.dist-info/WHEEL
pear_xai-0.0.10.dist-info/top_level.txt
pear_xai-0.0.10.dist-info/RECORD
