Metadata-Version: 2.1
Name: pear-xai
Version: 0.0.10
Summary: PEAR: Post-hoc Explainer Agreement Regularization
Author-email: Avi Schwarzschild <avi1@umd.edu>, Max Cembalest <max.cembalest@arthur.ai>, Karthik Rao <karthik@arthur.ai>
Maintainer-email: Avi Schwarzschild <avi1@umd.edu>, Max Cembalest <max.cembalest@arthur.ai>, Karthik Rao <karthik@arthur.ai>
License: BSD-3-Clause
Project-URL: homepage, https://arthur.ai
Project-URL: repository, https://github.com/aks2203/pear-xai
Project-URL: documentation, https://github.com/aks2203/pear-xai
Keywords: pytorch,XAI,machine learning
Requires-Python: >=3.9
License-File: LICENSE
Requires-Dist: jupyter (==1.0.0)
Requires-Dist: lime (==0.2.0.1)
Requires-Dist: matplotlib (==3.5.2)
Requires-Dist: numpy (==1.23.2)
Requires-Dist: torch (==1.11.0)
Requires-Dist: scikit-learn (==1.2.2)
Requires-Dist: seaborn (==0.12.2)
Requires-Dist: shap (==0.41.0)
Requires-Dist: sklearn (==0.0)
Requires-Dist: tabulate (==0.8.10)
Requires-Dist: torchvision (==0.12.0)
Requires-Dist: tqdm (==4.64.0)
